veda_bm/__init__.py
veda_bm-0.0.1a14.dist-info/LICENSE
veda_bm-0.0.1a14.dist-info/METADATA
veda_bm-0.0.1a14.dist-info/WHEEL
veda_bm-0.0.1a14.dist-info/top_level.txt
veda_bm-0.0.1a14.dist-info/RECORD
