Metadata-Version: 2.1
Name: veda_bm
Version: 0.0.1a14
Home-page: https://github.com/NASA-IMPACT/veda-black-marble
Author: VEDA Developers
Author-email: dimuthuw@gatech.edu
Project-URL: Bug Tracker, https://github.com/NASA-IMPACT/veda-black-marble/issues
Classifier: Programming Language :: Python :: 3
Classifier: License :: OSI Approved :: Apache Software License
Classifier: Operating System :: OS Independent
Requires-Python: >=3.6
License-File: LICENSE
Requires-Dist: boto3 >=1.28.82
